<?xml version="1.0" encoding="UTF-8"?>
<xwikidoc>
<web>Disciplines</web>
<name>AncientLanguagesAndCulture</name>
<language></language>
<defaultLanguage>en</defaultLanguage>
<translation>0</translation>
<parent>Disciplines.WorldLanguages</parent>
<creator>XWiki.Admin</creator>
<author>XWiki.Admin</author>
<customClass></customClass>
<contentAuthor>XWiki.Admin</contentAuthor>
<creationDate>1334160641000</creationDate>
<date>1334160641000</date>
<contentUpdateDate>1334160641000</contentUpdateDate>
<version>1.1</version>
<title>Langues et cultures de l'Antiquité (latin,grec ancien)</title>
<template></template>
<defaultTemplate></defaultTemplate>
<validationScript></validationScript>
<comment></comment>
<minorEdit>false</minorEdit>
<syntaxId>xwiki/2.0</syntaxId>
<hidden>false</hidden>
<object>
<class>
<name>CurrikiCode.DisciplineClass</name>
<customClass></customClass>
<customMapping></customMapping>
<defaultViewSheet></defaultViewSheet>
<defaultEditSheet></defaultEditSheet>
<defaultWeb></defaultWeb>
<nameField></nameField>
<validationScript></validationScript>
<educational_levels>
<cache>0</cache>
<classname></classname>
<customDisplay></customDisplay>
<disabled>0</disabled>
<displayType>checkbox</displayType>
<idField></idField>
<multiSelect>1</multiSelect>
<name>educational_levels</name>
<number>2</number>
<picker>0</picker>
<prettyName>Educational levels</prettyName>
<relationalStorage>0</relationalStorage>
<separator> </separator>
<separators></separators>
<size>1</size>
<sort>none</sort>
<sql>select doc.fullName, doc.title from XWikiDocument as doc, BaseObject as obj where doc.space in ('AssetMetadata') and doc.fullName=obj.name and obj.className='CurrikiCode.EducationalLevelClass' order by doc.fullName
</sql><unmodifiable>0</unmodifiable>
<validationMessage></validationMessage>
<validationRegExp></validationRegExp>
<valueField></valueField>
<classType>com.xpn.xwiki.objects.classes.DBListClass</classType>
</educational_levels>
<id>
<customDisplay></customDisplay>
<disabled>0</disabled>
<name>id</name>
<number>1</number>
<picker>0</picker>
<prettyName>Id</prettyName>
<size>30</size>
<unmodifiable>0</unmodifiable>
<validationMessage></validationMessage>
<validationRegExp></validationRegExp>
<classType>com.xpn.xwiki.objects.classes.StringClass</classType>
</id>
</class>
<name>Disciplines.AncientLanguagesAndCulture</name>
<number>0</number>
<className>CurrikiCode.DisciplineClass</className>
<guid>10cb9158-a178-49e6-9978-ca32ecd9edfc</guid>
<property>
<educational_levels>
<value>AssetMetadata.89</value>
<value>AssetMetadata.FRCollege</value>
<value>AssetMetadata.FRLycee</value>
<value>AssetMetadata.FRProfessionnel</value>
<value>AssetMetadata.USK2</value>
<value>AssetMetadata.SNCollege</value>
<value>AssetMetadata.SNLycee</value>
<value>AssetMetadata.SNSuperiorTechEducation</value>
</educational_levels>
</property>
<property>
<id></id>
</property>
<property>
<pivot></pivot>
</property>
</object>
<content>{{include document="CurrikiCode.DisciplineSheet"/}}</content></xwikidoc>